zignode/__init__.py
zignode/core.py
zignode-25.2.dist-info/licenses/LICENSE
zignode-25.2.dist-info/METADATA
zignode-25.2.dist-info/WHEEL
zignode-25.2.dist-info/top_level.txt
zignode-25.2.dist-info/RECORD
